chatnificent/__init__.py
chatnificent/auth.py
chatnificent/callbacks.py
chatnificent/engine.py
chatnificent/layout.py
chatnificent/llm.py
chatnificent/models.py
chatnificent/py.typed
chatnificent/retrieval.py
chatnificent/store.py
chatnificent/tools.py
chatnificent/url.py
chatnificent-0.0.10.dist-info/WHEEL
chatnificent-0.0.10.dist-info/METADATA
chatnificent-0.0.10.dist-info/RECORD
