Metadata-Version: 2.3
Name: chatnificent
Version: 0.0.10
Summary: LLM chat app framework - Minimally complete. Maximally hackable
Keywords: llm,chatbot,chat,ai,flask,dash,web-framework,openai,anthropic,conversational-ai
Author: Elias Dabbas
Author-email: Elias Dabbas <eliasdabbas@gmail.com>
Classifier: Development Status :: 3 - Alpha
Classifier: Environment :: Web Environment
Classifier: Framework :: Dash
Classifier: Intended Audience :: Developers
Classifier: License :: OSI Approved :: MIT License
Classifier: Operating System :: OS Independent
Classifier: Programming Language :: Python :: 3
Classifier: Programming Language :: Python :: 3.9
Classifier: Programming Language :: Python :: 3.10
Classifier: Programming Language :: Python :: 3.11
Classifier: Programming Language :: Python :: 3.12
Classifier: Programming Language :: Python :: 3.13
Classifier: Topic :: Communications :: Chat
Classifier: Topic :: Internet :: WWW/HTTP :: Dynamic Content
Classifier: Topic :: Internet :: WWW/HTTP :: WSGI :: Application
Classifier: Topic :: Scientific/Engineering :: Artificial Intelligence
Classifier: Topic :: Software Development :: Libraries :: Application Frameworks
Classifier: Topic :: Software Development :: Libraries :: Python Modules
Classifier: Topic :: Software Development :: User Interfaces
Classifier: Typing :: Typed
Requires-Dist: dash>=3.0.0
Requires-Dist: pydantic>=2.0.0
Requires-Dist: dash-bootstrap-components>=2.0.0 ; extra == 'default'
Requires-Dist: openai>=1.0.0 ; extra == 'default'
Requires-Dist: dash-mantine-components>=1.1.0 ; extra == 'mantine'
Requires-Dist: dash-iconify==0.1.2 ; extra == 'mantine'
Requires-Python: >=3.9
Project-URL: Bug Tracker, https://github.com/eliasdabbas/chatnificent/issues
Project-URL: Homepage, https://github.com/eliasdabbas/chatnificent
Project-URL: Repository, https://github.com/eliasdabbas/chatnificent
Provides-Extra: default
Provides-Extra: mantine
